dotlock/__init__.py
dotlock/__main__.py
dotlock/bundle.py
dotlock/env.py
dotlock/exceptions.py
dotlock/graph.py
dotlock/init.py
dotlock/install.py
dotlock/install.sh
dotlock/install_skip_lock.py
dotlock/json.py
dotlock/markers.py
dotlock/package.skeleton.json
dotlock/package_json.py
dotlock/package_lock.py
dotlock/resolve.py
dotlock/run.py
dotlock/tempdir.py
dotlock/_vendored/__init__.py
dotlock/_vendored/appdirs.py
dotlock/_vendored/compat.py
dotlock/_vendored/glibc.py
dotlock/_vendored/pep425tags.py
dotlock/dist_info/__init__.py
dotlock/dist_info/cache_schema.sql
dotlock/dist_info/caching.py
dotlock/dist_info/dist_info.py
dotlock/dist_info/json_api.py
dotlock/dist_info/package_indices.py
dotlock/dist_info/sdist_handling.py
dotlock/dist_info/simple_api.py
dotlock/dist_info/vcs.py
dotlock/dist_info/wheel_filename_parsing.py
dotlock/dist_info/wheel_handling.py
dotlock-0.8.1.dist-info/LICENSE.txt
dotlock-0.8.1.dist-info/METADATA
dotlock-0.8.1.dist-info/WHEEL
dotlock-0.8.1.dist-info/entry_points.txt
dotlock-0.8.1.dist-info/top_level.txt
dotlock-0.8.1.dist-info/RECORD
